sppe.v
`timescale 1ns / 1ps

module sppe #(
    parameter N = 16,
    parameter MODULUS = 12289
)(
    input  wire        Clk,
    input  wire        Reset,
    input  wire        Start,
    input  wire        input_valid,
    input  wire [15:0] input_coeff_data,
    input  wire        operand_sel,        // 0: Poly A, 1: Poly B
    output reg  [15:0] output_coeff_data,
    output reg         output_valid,
    output reg         busy,
    output reg         done
);

    reg [15:0] a_mem [0:N-1];
    reg [15:0] b_mem [0:N-1];
    reg [15:0] c_mem [0:N-1];

    reg [3:0] in_idx_a;
    reg [3:0] in_idx_b;
    reg [3:0] i_idx, j_idx;
    reg [4:0] out_idx;
    reg [31:0] accum;

    localparam IDLE    = 3'd0,
               COMPUTE = 3'd1,
               REDUCE  = 3'd2,
               STREAM  = 3'd3,
               FINISH  = 3'd4;

    reg [2:0] state;

    always @(posedge Clk or posedge Reset) begin
        if (Reset) begin
            in_idx_a <= 4'd0;
            in_idx_b <= 4'd0;
        end else if (input_valid && !busy) begin
            if (operand_sel == 1'b0) begin
                a_mem[in_idx_a] <= input_coeff_data % MODULUS;
                in_idx_a <= in_idx_a + 1'b1;
            end else begin
                b_mem[in_idx_b] <= input_coeff_data % MODULUS;
                in_idx_b <= in_idx_b + 1'b1;
            end
        end
    end

    always @(posedge Clk or posedge Reset) begin
        if (Reset) begin
            state             <= IDLE;
            busy              <= 1'b0;
            done              <= 1'b0;
            output_valid      <= 1'b0;
            output_coeff_data <= 16'd0;
            i_idx             <= 4'd0;
            j_idx             <= 4'd0;
            out_idx           <= 5'd0;
            accum             <= 32'd0;
        end else begin
            case (state)
                IDLE: begin
                    done         <= 1'b0;
                    output_valid <= 1'b0;
                    if (Start) begin
                        busy    <= 1'b1;
                        i_idx   <= 4'd0;
                        j_idx   <= 4'd0;
                        accum   <= 32'd0;
                        state   <= COMPUTE;
                    end else begin
                        busy    <= 1'b0;
                    end
                end

                COMPUTE: begin
                    if (j_idx <= i_idx) begin
                        accum <= accum + (a_mem[j_idx] * b_mem[i_idx - j_idx]);
                    end else begin
                        accum <= accum + ((MODULUS - a_mem[j_idx]) * b_mem[N + i_idx - j_idx]);
                    end

                    if (j_idx == N - 1) begin
                        j_idx <= 4'd0;
                        state <= REDUCE;
                    end else begin
                        j_idx <= j_idx + 1'b1;
                    end
                end

                REDUCE: begin
                    c_mem[i_idx] <= accum % MODULUS;
                    accum        <= 32'd0;
                    if (i_idx == N - 1) begin
                        out_idx <= 5'd0;
                        state   <= STREAM;
                    end else begin
                        i_idx   <= i_idx + 1'b1;
                        state   <= COMPUTE;
                    end
                end

                STREAM: begin
                    if (out_idx < N) begin
                        output_coeff_data <= c_mem[out_idx[3:0]];
                        output_valid      <= 1'b1;
                        out_idx           <= out_idx + 1'b1;
                    end else begin
                        output_valid      <= 1'b0;
                        done              <= 1'b1;
                        state             <= FINISH;
                    end
                end

                FINISH: begin
                    busy  <= 1'b0;
                    done  <= 1'b1;
                    state <= IDLE;
                end

                default: state <= IDLE;
            endcase
        end
    end

endmodule

sppe_tb.v
`timescale 1ns / 1ps

module sppe_tb;

    localparam N = 16;
    localparam MODULUS = 12289;

    reg         clk;
    reg         reset;
    reg         start;
    reg         input_valid;
    reg  [15:0] input_coeff_data;
    reg         operand_sel;

    wire [15:0] output_coeff_data;
    wire        output_valid;
    wire        busy;
    wire        done;

    sppe #(.N(N), .MODULUS(MODULUS)) uut (
        .Clk(clk),
        .Reset(reset),
        .Start(start),
        .input_valid(input_valid),
        .input_coeff_data(input_coeff_data),
        .operand_sel(operand_sel),
        .output_coeff_data(output_coeff_data),
        .output_valid(output_valid),
        .busy(busy),
        .done(done)
    );

    always #5 clk = ~clk;

    integer k;
    reg [15:0] test_a [0:15];
    reg [15:0] test_b [0:15];

    initial begin
        $dumpfile("sppe.vcd");
        $dumpvars(0, sppe_tb);  // Use the exact module name of your testbench
        clk = 0;
        reset = 1;
        start = 0;
        input_valid = 0;
        input_coeff_data = 0;
        operand_sel = 0;

        // Initialize test vectors: A = [1, 2, ..., 16], B = [1, 0, 0, ..., 0] (Identity)
        for (k = 0; k < 16; k = k + 1) begin
            test_a[k] = k + 1;
            test_b[k] = (k == 0) ? 16'd1 : 16'd0;
        end

        #20 reset = 0;
        #10;

        // Load Polynomial A
        for (k = 0; k < 16; k = k + 1) begin
            @(posedge clk);
            operand_sel = 1'b0;
            input_valid = 1'b1;
            input_coeff_data = test_a[k];
        end

        // Load Polynomial B
        for (k = 0; k < 16; k = k + 1) begin
            @(posedge clk);
            operand_sel = 1'b1;
            input_valid = 1'b1;
            input_coeff_data = test_b[k];
        end

        @(posedge clk);
        input_valid = 1'b0;

        // Trigger Multiplication
        @(posedge clk);
        start = 1'b1;
        @(posedge clk);
        start = 1'b0;

        // Monitor & Verify
        wait(done);
        #30;
        $display(">> Test Completed Successfully!");
        $finish;
    end

    always @(posedge clk) begin
        if (output_valid) begin
            $display("[OUTPUT] Coeff received: %0d", output_coeff_data);
        end
    end

endmodule

sppe.vcd
$date
	Wed Aug 19 08:49:38 2026
$end
$version
	Icarus Verilog
$end
$timescale
	1ps
$end
$scope module sppe_tb $end
$var wire 1 ! output_valid $end
$var wire 16 " output_coeff_data [15:0] $end
$var wire 1 # done $end
$var wire 1 $ busy $end
$var reg 1 % clk $end
$var reg 16 & input_coeff_data [15:0] $end
$var reg 1 ' input_valid $end
$var reg 1 ( operand_sel $end
$var reg 1 ) reset $end
$var reg 1 * start $end
$var integer 32 + k [31:0] $end
$scope module uut $end
$var wire 1 % Clk $end
$var wire 1 ) Reset $end
$var wire 1 * Start $end
$var wire 16 , input_coeff_data [15:0] $end
$var wire 1 ' input_valid $end
$var wire 1 ( operand_sel $end
$var reg 32 - accum [31:0] $end
$var reg 1 $ busy $end
$var reg 1 # done $end
$var reg 4 . i_idx [3:0] $end
$var reg 4 / in_idx_a [3:0] $end
$var reg 4 0 in_idx_b [3:0] $end
$var reg 4 1 j_idx [3:0] $end
$var reg 5 2 out_idx [4:0] $end
$var reg 16 3 output_coeff_data [15:0] $end
$var reg 1 ! output_valid $end
$var reg 3 4 state [2:0] $end
$upscope $end
$upscope $end
$enddefinitions $end
#0
$dumpvars
b0 4
b0 3
b0 2
b0 1
b0 0
b0 /
b0 .
b0 -
b0 ,
b10000 +
0*
1)
0(
0'
b0 &
0%
0$
0#
b0 "
0!
$end
#5000
1%
#10000
0%
#15000
1%
#20000
0%
0)
#25000
1%
#30000
0%
b0 +
#35000
b1 /
b1 +
b1 &
b1 ,
1'
1%
#40000
0%
#45000
b10 /
b10 +
b10 &
b10 ,
1%
#50000
0%
#55000
b11 /
b11 +
b11 &
b11 ,
1%
#60000
0%
#65000
b100 /
b100 +
b100 &
b100 ,
1%
#70000
0%
#75000
b101 /
b101 +
b101 &
b101 ,
1%
#80000
0%
#85000
b110 /
b110 +
b110 &
b110 ,
1%
#90000
0%
#95000
b111 /
b111 +
b111 &
b111 ,
1%
#100000
0%
#105000
b1000 /
b1000 +
b1000 &
b1000 ,
1%
#110000
0%
#115000
b1001 /
b1001 +
b1001 &
b1001 ,
1%
#120000
0%
#125000
b1010 /
b1010 +
b1010 &
b1010 ,
1%
#130000
0%
#135000
b1011 /
b1011 +
b1011 &
b1011 ,
1%
#140000
0%
#145000
b1100 /
b1100 +
b1100 &
b1100 ,
1%
#150000
0%
#155000
b1101 /
b1101 +
b1101 &
b1101 ,
1%
#160000
0%
#165000
b1110 /
b1110 +
b1110 &
b1110 ,
1%
#170000
0%
#175000
b1111 /
b1111 +
b1111 &
b1111 ,
1%
#180000
0%
#185000
b0 /
b0 +
b10000 &
b10000 ,
1%
#190000
0%
#195000
b1 0
b1 +
b1 &
b1 ,
1(
1%
#200000
0%
#205000
b10 0
b10 +
b0 &
b0 ,
1%
#210000
0%
#215000
b11 0
b11 +
1%
#220000
0%
#225000
b100 0
b100 +
1%
#230000
0%
#235000
b101 0
b101 +
1%
#240000
0%
#245000
b110 0
b110 +
1%
#250000
0%
#255000
b111 0
b111 +
1%
#260000
0%
#265000
b1000 0
b1000 +
1%
#270000
0%
#275000
b1001 0
b1001 +
1%
#280000
0%
#285000
b1010 0
b1010 +
1%
#290000
0%
#295000
b1011 0
b1011 +
1%
#300000
0%
#305000
b1100 0
b1100 +
1%
#310000
0%
#315000
b1101 0
b1101 +
1%
#320000
0%
#325000
b1110 0
b1110 +
1%
#330000
0%
#335000
b1111 0
b1111 +
1%
#340000
0%
#345000
b0 0
b10000 +
1%
#350000
0%
#355000
0'
1%
#360000
0%
#365000
b1 4
1$
1*
1%
#370000
0%
#375000
b1 1
b1 -
0*
1%
#380000
0%
#385000
b10 1
1%
#390000
0%
#395000
b11 1
1%
#400000
0%
#405000
b100 1
1%
#410000
0%
#415000
b101 1
1%
#420000
0%
#425000
b110 1
1%
#430000
0%
#435000
b111 1
1%
#440000
0%
#445000
b1000 1
1%
#450000
0%
#455000
b1001 1
1%
#460000
0%
#465000
b1010 1
1%
#470000
0%
#475000
b1011 1
1%
#480000
0%
#485000
b1100 1
1%
#490000
0%
#495000
b1101 1
1%
#500000
0%
#505000
b1110 1
1%
#510000
0%
#515000
b1111 1
1%
#520000
0%
#525000
b10 4
b0 1
1%
#530000
0%
#535000
b1 4
b1 .
b0 -
1%
#540000
0%
#545000
b1 1
1%
#550000
0%
#555000
b10 1
b10 -
1%
#560000
0%
#565000
b11 1
1%
#570000
0%
#575000
b100 1
1%
#580000
0%
#585000
b101 1
1%
#590000
0%
#595000
b110 1
1%
#600000
0%
#605000
b111 1
1%
#610000
0%
#615000
b1000 1
1%
#620000
0%
#625000
b1001 1
1%
#630000
0%
#635000
b1010 1
1%
#640000
0%
#645000
b1011 1
1%
#650000
0%
#655000
b1100 1
1%
#660000
0%
#665000
b1101 1
1%
#670000
0%
#675000
b1110 1
1%
#680000
0%
#685000
b1111 1
1%
#690000
0%
#695000
b10 4
b0 1
1%
#700000
0%
#705000
b1 4
b10 .
b0 -
1%
#710000
0%
#715000
b1 1
1%
#720000
0%
#725000
b10 1
1%
#730000
0%
#735000
b11 1
b11 -
1%
#740000
0%
#745000
b100 1
1%
#750000
0%
#755000
b101 1
1%
#760000
0%
#765000
b110 1
1%
#770000
0%
#775000
b111 1
1%
#780000
0%
#785000
b1000 1
1%
#790000
0%
#795000
b1001 1
1%
#800000
0%
#805000
b1010 1
1%
#810000
0%
#815000
b1011 1
1%
#820000
0%
#825000
b1100 1
1%
#830000
0%
#835000
b1101 1
1%
#840000
0%
#845000
b1110 1
1%
#850000
0%
#855000
b1111 1
1%
#860000
0%
#865000
b10 4
b0 1
1%
#870000
0%
#875000
b1 4
b11 .
b0 -
1%
#880000
0%
#885000
b1 1
1%
#890000
0%
#895000
b10 1
1%
#900000
0%
#905000
b11 1
1%
#910000
0%
#915000
b100 1
b100 -
1%
#920000
0%
#925000
b101 1
1%
#930000
0%
#935000
b110 1
1%
#940000
0%
#945000
b111 1
1%
#950000
0%
#955000
b1000 1
1%
#960000
0%
#965000
b1001 1
1%
#970000
0%
#975000
b1010 1
1%
#980000
0%
#985000
b1011 1
1%
#990000
0%
#995000
b1100 1
1%
#1000000
0%
#1005000
b1101 1
1%
#1010000
0%
#1015000
b1110 1
1%
#1020000
0%
#1025000
b1111 1
1%
#1030000
0%
#1035000
b10 4
b0 1
1%
#1040000
0%
#1045000
b1 4
b100 .
b0 -
1%
#1050000
0%
#1055000
b1 1
1%
#1060000
0%
#1065000
b10 1
1%
#1070000
0%
#1075000
b11 1
1%
#1080000
0%
#1085000
b100 1
1%
#1090000
0%
#1095000
b101 1
b101 -
1%
#1100000
0%
#1105000
b110 1
1%
#1110000
0%
#1115000
b111 1
1%
#1120000
0%
#1125000
b1000 1
1%
#1130000
0%
#1135000
b1001 1
1%
#1140000
0%
#1145000
b1010 1
1%
#1150000
0%
#1155000
b1011 1
1%
#1160000
0%
#1165000
b1100 1
1%
#1170000
0%
#1175000
b1101 1
1%
#1180000
0%
#1185000
b1110 1
1%
#1190000
0%
#1195000
b1111 1
1%
#1200000
0%
#1205000
b10 4
b0 1
1%
#1210000
0%
#1215000
b1 4
b101 .
b0 -
1%
#1220000
0%
#1225000
b1 1
1%
#1230000
0%
#1235000
b10 1
1%
#1240000
0%
#1245000
b11 1
1%
#1250000
0%
#1255000
b100 1
1%
#1260000
0%
#1265000
b101 1
1%
#1270000
0%
#1275000
b110 1
b110 -
1%
#1280000
0%
#1285000
b111 1
1%
#1290000
0%
#1295000
b1000 1
1%
#1300000
0%
#1305000
b1001 1
1%
#1310000
0%
#1315000
b1010 1
1%
#1320000
0%
#1325000
b1011 1
1%
#1330000
0%
#1335000
b1100 1
1%
#1340000
0%
#1345000
b1101 1
1%
#1350000
0%
#1355000
b1110 1
1%
#1360000
0%
#1365000
b1111 1
1%
#1370000
0%
#1375000
b10 4
b0 1
1%
#1380000
0%
#1385000
b1 4
b110 .
b0 -
1%
#1390000
0%
#1395000
b1 1
1%
#1400000
0%
#1405000
b10 1
1%
#1410000
0%
#1415000
b11 1
1%
#1420000
0%
#1425000
b100 1
1%
#1430000
0%
#1435000
b101 1
1%
#1440000
0%
#1445000
b110 1
1%
#1450000
0%
#1455000
b111 1
b111 -
1%
#1460000
0%
#1465000
b1000 1
1%
#1470000
0%
#1475000
b1001 1
1%
#1480000
0%
#1485000
b1010 1
1%
#1490000
0%
#1495000
b1011 1
1%
#1500000
0%
#1505000
b1100 1
1%
#1510000
0%
#1515000
b1101 1
1%
#1520000
0%
#1525000
b1110 1
1%
#1530000
0%
#1535000
b1111 1
1%
#1540000
0%
#1545000
b10 4
b0 1
1%
#1550000
0%
#1555000
b1 4
b111 .
b0 -
1%
#1560000
0%
#1565000
b1 1
1%
#1570000
0%
#1575000
b10 1
1%
#1580000
0%
#1585000
b11 1
1%
#1590000
0%
#1595000
b100 1
1%
#1600000
0%
#1605000
b101 1
1%
#1610000
0%
#1615000
b110 1
1%
#1620000
0%
#1625000
b111 1
1%
#1630000
0%
#1635000
b1000 1
b1000 -
1%
#1640000
0%
#1645000
b1001 1
1%
#1650000
0%
#1655000
b1010 1
1%
#1660000
0%
#1665000
b1011 1
1%
#1670000
0%
#1675000
b1100 1
1%
#1680000
0%
#1685000
b1101 1
1%
#1690000
0%
#1695000
b1110 1
1%
#1700000
0%
#1705000
b1111 1
1%
#1710000
0%
#1715000
b10 4
b0 1
1%
#1720000
0%
#1725000
b1 4
b1000 .
b0 -
1%
#1730000
0%
#1735000
b1 1
1%
#1740000
0%
#1745000
b10 1
1%
#1750000
0%
#1755000
b11 1
1%
#1760000
0%
#1765000
b100 1
1%
#1770000
0%
#1775000
b101 1
1%
#1780000
0%
#1785000
b110 1
1%
#1790000
0%
#1795000
b111 1
1%
#1800000
0%
#1805000
b1000 1
1%
#1810000
0%
#1815000
b1001 1
b1001 -
1%
#1820000
0%
#1825000
b1010 1
1%
#1830000
0%
#1835000
b1011 1
1%
#1840000
0%
#1845000
b1100 1
1%
#1850000
0%
#1855000
b1101 1
1%
#1860000
0%
#1865000
b1110 1
1%
#1870000
0%
#1875000
b1111 1
1%
#1880000
0%
#1885000
b10 4
b0 1
1%
#1890000
0%
#1895000
b1 4
b1001 .
b0 -
1%
#1900000
0%
#1905000
b1 1
1%
#1910000
0%
#1915000
b10 1
1%
#1920000
0%
#1925000
b11 1
1%
#1930000
0%
#1935000
b100 1
1%
#1940000
0%
#1945000
b101 1
1%
#1950000
0%
#1955000
b110 1
1%
#1960000
0%
#1965000
b111 1
1%
#1970000
0%
#1975000
b1000 1
1%
#1980000
0%
#1985000
b1001 1
1%
#1990000
0%
#1995000
b1010 1
b1010 -
1%
#2000000
0%
#2005000
b1011 1
1%
#2010000
0%
#2015000
b1100 1
1%
#2020000
0%
#2025000
b1101 1
1%
#2030000
0%
#2035000
b1110 1
1%
#2040000
0%
#2045000
b1111 1
1%
#2050000
0%
#2055000
b10 4
b0 1
1%
#2060000
0%
#2065000
b1 4
b1010 .
b0 -
1%
#2070000
0%
#2075000
b1 1
1%
#2080000
0%
#2085000
b10 1
1%
#2090000
0%
#2095000
b11 1
1%
#2100000
0%
#2105000
b100 1
1%
#2110000
0%
#2115000
b101 1
1%
#2120000
0%
#2125000
b110 1
1%
#2130000
0%
#2135000
b111 1
1%
#2140000
0%
#2145000
b1000 1
1%
#2150000
0%
#2155000
b1001 1
1%
#2160000
0%
#2165000
b1010 1
1%
#2170000
0%
#2175000
b1011 1
b1011 -
1%
#2180000
0%
#2185000
b1100 1
1%
#2190000
0%
#2195000
b1101 1
1%
#2200000
0%
#2205000
b1110 1
1%
#2210000
0%
#2215000
b1111 1
1%
#2220000
0%
#2225000
b10 4
b0 1
1%
#2230000
0%
#2235000
b1 4
b1011 .
b0 -
1%
#2240000
0%
#2245000
b1 1
1%
#2250000
0%
#2255000
b10 1
1%
#2260000
0%
#2265000
b11 1
1%
#2270000
0%
#2275000
b100 1
1%
#2280000
0%
#2285000
b101 1
1%
#2290000
0%
#2295000
b110 1
1%
#2300000
0%
#2305000
b111 1
1%
#2310000
0%
#2315000
b1000 1
1%
#2320000
0%
#2325000
b1001 1
1%
#2330000
0%
#2335000
b1010 1
1%
#2340000
0%
#2345000
b1011 1
1%
#2350000
0%
#2355000
b1100 1
b1100 -
1%
#2360000
0%
#2365000
b1101 1
1%
#2370000
0%
#2375000
b1110 1
1%
#2380000
0%
#2385000
b1111 1
1%
#2390000
0%
#2395000
b10 4
b0 1
1%
#2400000
0%
#2405000
b1 4
b1100 .
b0 -
1%
#2410000
0%
#2415000
b1 1
1%
#2420000
0%
#2425000
b10 1
1%
#2430000
0%
#2435000
b11 1
1%
#2440000
0%
#2445000
b100 1
1%
#2450000
0%
#2455000
b101 1
1%
#2460000
0%
#2465000
b110 1
1%
#2470000
0%
#2475000
b111 1
1%
#2480000
0%
#2485000
b1000 1
1%
#2490000
0%
#2495000
b1001 1
1%
#2500000
0%
#2505000
b1010 1
1%
#2510000
0%
#2515000
b1011 1
1%
#2520000
0%
#2525000
b1100 1
1%
#2530000
0%
#2535000
b1101 1
b1101 -
1%
#2540000
0%
#2545000
b1110 1
1%
#2550000
0%
#2555000
b1111 1
1%
#2560000
0%
#2565000
b10 4
b0 1
1%
#2570000
0%
#2575000
b1 4
b1101 .
b0 -
1%
#2580000
0%
#2585000
b1 1
1%
#2590000
0%
#2595000
b10 1
1%
#2600000
0%
#2605000
b11 1
1%
#2610000
0%
#2615000
b100 1
1%
#2620000
0%
#2625000
b101 1
1%
#2630000
0%
#2635000
b110 1
1%
#2640000
0%
#2645000
b111 1
1%
#2650000
0%
#2655000
b1000 1
1%
#2660000
0%
#2665000
b1001 1
1%
#2670000
0%
#2675000
b1010 1
1%
#2680000
0%
#2685000
b1011 1
1%
#2690000
0%
#2695000
b1100 1
1%
#2700000
0%
#2705000
b1101 1
1%
#2710000
0%
#2715000
b1110 1
b1110 -
1%
#2720000
0%
#2725000
b1111 1
1%
#2730000
0%
#2735000
b10 4
b0 1
1%
#2740000
0%
#2745000
b1 4
b1110 .
b0 -
1%
#2750000
0%
#2755000
b1 1
1%
#2760000
0%
#2765000
b10 1
1%
#2770000
0%
#2775000
b11 1
1%
#2780000
0%
#2785000
b100 1
1%
#2790000
0%
#2795000
b101 1
1%
#2800000
0%
#2805000
b110 1
1%
#2810000
0%
#2815000
b111 1
1%
#2820000
0%
#2825000
b1000 1
1%
#2830000
0%
#2835000
b1001 1
1%
#2840000
0%
#2845000
b1010 1
1%
#2850000
0%
#2855000
b1011 1
1%
#2860000
0%
#2865000
b1100 1
1%
#2870000
0%
#2875000
b1101 1
1%
#2880000
0%
#2885000
b1110 1
1%
#2890000
0%
#2895000
b1111 1
b1111 -
1%
#2900000
0%
#2905000
b10 4
b0 1
1%
#2910000
0%
#2915000
b1 4
b1111 .
b0 -
1%
#2920000
0%
#2925000
b1 1
1%
#2930000
0%
#2935000
b10 1
1%
#2940000
0%
#2945000
b11 1
1%
#2950000
0%
#2955000
b100 1
1%
#2960000
0%
#2965000
b101 1
1%
#2970000
0%
#2975000
b110 1
1%
#2980000
0%
#2985000
b111 1
1%
#2990000
0%
#2995000
b1000 1
1%
#3000000
0%
#3005000
b1001 1
1%
#3010000
0%
#3015000
b1010 1
1%
#3020000
0%
#3025000
b1011 1
1%
#3030000
0%
#3035000
b1100 1
1%
#3040000
0%
#3045000
b1101 1
1%
#3050000
0%
#3055000
b1110 1
1%
#3060000
0%
#3065000
b1111 1
1%
#3070000
0%
#3075000
b10 4
b0 1
b10000 -
1%
#3080000
0%
#3085000
b11 4
b0 -
1%
#3090000
0%
#3095000
b1 2
1!
b1 "
b1 3
1%
#3100000
0%
#3105000
b10 2
b10 "
b10 3
1%
#3110000
0%
#3115000
b11 2
b11 "
b11 3
1%
#3120000
0%
#3125000
b100 2
b100 "
b100 3
1%
#3130000
0%
#3135000
b101 2
b101 "
b101 3
1%
#3140000
0%
#3145000
b110 2
b110 "
b110 3
1%
#3150000
0%
#3155000
b111 2
b111 "
b111 3
1%
#3160000
0%
#3165000
b1000 2
b1000 "
b1000 3
1%
#3170000
0%
#3175000
b1001 2
b1001 "
b1001 3
1%
#3180000
0%
#3185000
b1010 2
b1010 "
b1010 3
1%
#3190000
0%
#3195000
b1011 2
b1011 "
b1011 3
1%
#3200000
0%
#3205000
b1100 2
b1100 "
b1100 3
1%
#3210000
0%
#3215000
b1101 2
b1101 "
b1101 3
1%
#3220000
0%
#3225000
b1110 2
b1110 "
b1110 3
1%
#3230000
0%
#3235000
b1111 2
b1111 "
b1111 3
1%
#3240000
0%
#3245000
b10000 2
b10000 "
b10000 3
1%
#3250000
0%
#3255000
b100 4
1#
0!
1%
#3260000
0%
#3265000
b0 4
0$
1%
#3270000
0%
#3275000
0#
1%
